LICENSE
MANIFEST.in
README.md
setup.py
expfactory/__init__.py
expfactory/__main__.py
expfactory/api.py
expfactory/config_dummy.py
expfactory/defaults.py
expfactory/experiment.py
expfactory/forms.py
expfactory/server.py
expfactory/utils.py
expfactory/variables.py
expfactory/version.py
expfactory/wsgi.py
expfactory.egg-info/PKG-INFO
expfactory.egg-info/SOURCES.txt
expfactory.egg-info/dependency_links.txt
expfactory.egg-info/entry_points.txt
expfactory.egg-info/not-zip-safe
expfactory.egg-info/requires.txt
expfactory.egg-info/top_level.txt
expfactory/cli/__init__.py
expfactory/cli/build.py
expfactory/cli/install.py
expfactory/cli/list.py
expfactory/cli/logs.py
expfactory/cli/main.py
expfactory/cli/users.py
expfactory/database/__init__.py
expfactory/database/filesystem.py
expfactory/database/models.py
expfactory/database/relational.py
expfactory/database/sqlite.py
expfactory/logger/__init__.py
expfactory/logger/message.py
expfactory/logger/progress.py
expfactory/logger/spinner.py
expfactory/static/css/bootstrap-theme.css
expfactory/static/css/bootstrap-theme.css.map
expfactory/static/css/bootstrap-theme.min.css
expfactory/static/css/bootstrap.min.css
expfactory/static/css/style.css
expfactory/static/fonts/glyphicons-halflings-regular.eot
expfactory/static/fonts/glyphicons-halflings-regular.svg
expfactory/static/fonts/glyphicons-halflings-regular.ttf
expfactory/static/fonts/glyphicons-halflings-regular.woff
expfactory/static/fonts/glyphicons-halflings-regular.woff2
expfactory/static/img/expfactoryticket.png
expfactory/static/img/expfactoryticketyellow.png
expfactory/static/img/favicon.ico
expfactory/static/img/tinypeople.png
expfactory/static/img/tinypeople.svg
expfactory/static/img/icons/cancel.png
expfactory/static/img/icons/preloader.gif
expfactory/static/js/bootstrap.min.js
expfactory/static/js/tipsy.js
expfactory/templates/base.html
expfactory/templates/build/docker/Dockerfile.dev
expfactory/templates/build/docker/Dockerfile.https
expfactory/templates/build/docker/Dockerfile.template
expfactory/templates/build/docker/README.md
expfactory/templates/build/docker/startscript.sh
expfactory/templates/build/docker/builder/Dockerfile
expfactory/templates/build/docker/builder/README.md
